setup.py
bin/sprang
sprang/__init__.py
sprang/providers.py
sprang.egg-info/PKG-INFO
sprang.egg-info/SOURCES.txt
sprang.egg-info/dependency_links.txt
sprang.egg-info/top_level.txt