Metadata-Version: 1.0
Name: sprang
Version: 0.20
Summary: Helper shell script allowing posting and retrieving of text snippets via 'sprunge.us' pastebin service.
Home-page: http://github.com/jingleman/sprang
Author: JingleManSweep
Author-email: jinglemansweep@gmail.com
License: UNKNOWN
Platform: UNKNOWN
